{"time":{"updated":"Mar 14, 2022 05:43:00 UTC","updatedISO":"2022-03-14T05:43:00+00:00","updateduk":"Mar 14, 2022 at 05:43 GMT"},"disclaimer":"This data was produced from the CoinDesk Bitcoin Price Index (USD). Non-USD currency data converted using hourly conversion rate from openexchangerates.org","chartName":"Bitcoin","bpi":{"USD":{"code":"USD","symbol":"&#36;","rate":"38,497.1500","description":"United States Dollar","rate_float":38497.15},"GBP":{"code":"GBP","symbol":"&pound;","rate":"29,560.9606","description":"British Pound Sterling","rate_float":29560.9606},"EUR":{"code":"EUR","symbol":"&euro;","rate":"35,262.4655","description":"Euro","rate_float":35262.4655},"CNY":{"code":"CNY","symbol":"&yen;","rate":"40,202.5000","description":"Chinese Yuan","rate_float":40202.5}}}