{"time":{"updated":"Mar 31, 2022 08:42:00 UTC","updatedISO":"2022-03-31T08:42:00+00:00","updateduk":"Mar 31, 2022 at 09:42 BST"},"disclaimer":"This data was produced from the CoinDesk Bitcoin Price Index (USD). Non-USD currency data converted using hourly conversion rate from openexchangerates.org","chartName":"Bitcoin","bpi":{"USD":{"code":"USD","symbol":"&#36;","rate":"47,139.5042","description":"United States Dollar","rate_float":47139.5042},"GBP":{"code":"GBP","symbol":"&pound;","rate":"35,887.8702","description":"British Pound Sterling","rate_float":35887.8702},"EUR":{"code":"EUR","symbol":"&euro;","rate":"42,274.2360","description":"Euro","rate_float":42274.236},"CNY":{"code":"CNY","symbol":"&yen;","rate":"40,202.5000","description":"Chinese Yuan","rate_float":40202.5}}}