{"time":{"updated":"Mar 26, 2022 15:37:00 UTC","updatedISO":"2022-03-26T15:37:00+00:00","updateduk":"Mar 26, 2022 at 15:37 GMT"},"disclaimer":"This data was produced from the CoinDesk Bitcoin Price Index (USD). Non-USD currency data converted using hourly conversion rate from openexchangerates.org","chartName":"Bitcoin","bpi":{"USD":{"code":"USD","symbol":"&#36;","rate":"44,303.2388","description":"United States Dollar","rate_float":44303.2388},"GBP":{"code":"GBP","symbol":"&pound;","rate":"33,587.2157","description":"British Pound Sterling","rate_float":33587.2157},"EUR":{"code":"EUR","symbol":"&euro;","rate":"40,332.5168","description":"Euro","rate_float":40332.5168},"CNY":{"code":"CNY","symbol":"&yen;","rate":"40,202.5000","description":"Chinese Yuan","rate_float":40202.5}}}