{"time":{"updated":"Mar 14, 2022 18:31:00 UTC","updatedISO":"2022-03-14T18:31:00+00:00","updateduk":"Mar 14, 2022 at 18:31 GMT"},"disclaimer":"This data was produced from the CoinDesk Bitcoin Price Index (USD). Non-USD currency data converted using hourly conversion rate from openexchangerates.org","chartName":"Bitcoin","bpi":{"USD":{"code":"USD","symbol":"&#36;","rate":"38,490.9601","description":"United States Dollar","rate_float":38490.9601},"GBP":{"code":"GBP","symbol":"&pound;","rate":"29,546.6617","description":"British Pound Sterling","rate_float":29546.6617},"EUR":{"code":"EUR","symbol":"&euro;","rate":"35,071.3847","description":"Euro","rate_float":35071.3847},"CNY":{"code":"CNY","symbol":"&yen;","rate":"40,202.5000","description":"Chinese Yuan","rate_float":40202.5}}}